uipath_connectors/amazon_webservices/__init__.py
uipath_connectors/amazon_webservices/client.py
uipath_connectors/amazon_webservices/errors.py
uipath_connectors/amazon_webservices/py.typed
uipath_connectors/amazon_webservices/types.py
uipath_connectors/amazon_webservices/api/__init__.py
uipath_connectors/amazon_webservices/api/ebsattach_volume_to_instance/__init__.py
uipath_connectors/amazon_webservices/api/ebsattach_volume_to_instance/attach_volume_to_instance.py
uipath_connectors/amazon_webservices/api/ebscreate_volume/__init__.py
uipath_connectors/amazon_webservices/api/ebscreate_volume/create_volume.py
uipath_connectors/amazon_webservices/api/ebscreate_volume_snapshot/__init__.py
uipath_connectors/amazon_webservices/api/ebscreate_volume_snapshot/create_volume_snapshot.py
uipath_connectors/amazon_webservices/api/ebsdelete_volume/__init__.py
uipath_connectors/amazon_webservices/api/ebsdelete_volume/delete_volume.py
uipath_connectors/amazon_webservices/api/ebsdelete_volume_snapshot/__init__.py
uipath_connectors/amazon_webservices/api/ebsdelete_volume_snapshot/delete_snapshot.py
uipath_connectors/amazon_webservices/api/ebssnapshot/__init__.py
uipath_connectors/amazon_webservices/api/ebssnapshot/get_snapshot.py
uipath_connectors/amazon_webservices/api/ebsvolume/__init__.py
uipath_connectors/amazon_webservices/api/ebsvolume/get_volume.py
uipath_connectors/amazon_webservices/api/ebsvolume/get_volume_list.py
uipath_connectors/amazon_webservices/api/ec2/__init__.py
uipath_connectors/amazon_webservices/api/ec2/get_instance.py
uipath_connectors/amazon_webservices/api/ec2/get_instance_list.py
uipath_connectors/amazon_webservices/api/ec2detach_volume_from_instance/__init__.py
uipath_connectors/amazon_webservices/api/ec2detach_volume_from_instance/detach_volume_from_instance.py
uipath_connectors/amazon_webservices/api/ec2instance_volume/__init__.py
uipath_connectors/amazon_webservices/api/ec2instance_volume/get_instance_volumes.py
uipath_connectors_amazon_webservices-1.5.12.dev12.dist-info/METADATA
uipath_connectors_amazon_webservices-1.5.12.dev12.dist-info/WHEEL
uipath_connectors_amazon_webservices-1.5.12.dev12.dist-info/entry_points.txt
uipath_connectors_amazon_webservices-1.5.12.dev12.dist-info/top_level.txt
uipath_connectors_amazon_webservices-1.5.12.dev12.dist-info/RECORD
